{
  "session_id": "38c29234-0e5e-4d8e-a69b-46bdba3be5d5",
  "timestamp": "2026-05-23T12:05:13.579917Z",
  "customer_intent": "The customer wants to book a Botox appointment.",
  "key_details_collected": {
    "treatment_interest": "botox",
    "experience_level": "first-time",
    "booking_readiness": "ready to book"
  },
  "sop_gaps": [],
  "recommended_next_action": "Schedule the customer's Botox appointment at their preferred date and time.",
  "escalated": false,
  "escalation_reason": null
}